servestatic/__init__.py
servestatic/asgi.py
servestatic/base.py
servestatic/compress.py
servestatic/media_types.py
servestatic/middleware.py
servestatic/responders.py
servestatic/storage.py
servestatic/utils.py
servestatic/wsgi.py
servestatic/runserver_nostatic/__init__.py
servestatic/runserver_nostatic/management/__init__.py
servestatic/runserver_nostatic/management/commands/__init__.py
servestatic/runserver_nostatic/management/commands/runserver.py
servestatic-3.1.0.dist-info/METADATA
servestatic-3.1.0.dist-info/WHEEL
servestatic-3.1.0.dist-info/licenses/LICENSE.md
servestatic-3.1.0.dist-info/RECORD
