Metadata-Version: 2.4
Name: servestatic
Version: 3.1.0
Summary: Production-grade static file server for Python WSGI & ASGI.
Project-URL: Changelog, https://archmonger.github.io/ServeStatic/latest/changelog/
Project-URL: Documentation, https://archmonger.github.io/ServeStatic/
Project-URL: Source, https://github.com/Archmonger/ServeStatic
Author-email: Mark Bakhit <archiethemonger@gmail.com>
License-Expression: MIT
License-File: LICENSE.md
Keywords: asgi,django,http,server,static,staticfiles,wsgi
Classifier: Development Status :: 5 - Production/Stable
Classifier: Framework :: Django
Classifier: Intended Audience :: Developers
Classifier: License :: OSI Approved :: MIT License
Classifier: Operating System :: OS Independent
Classifier: Programming Language :: Python :: 3 :: Only
Classifier: Programming Language :: Python :: 3.9
Classifier: Programming Language :: Python :: 3.10
Classifier: Programming Language :: Python :: 3.11
Classifier: Programming Language :: Python :: 3.12
Classifier: Programming Language :: Python :: 3.13
Classifier: Topic :: Communications :: File Sharing
Classifier: Topic :: Internet :: WWW/HTTP
Classifier: Topic :: Internet :: WWW/HTTP :: WSGI :: Middleware
Requires-Python: >=3.9
Requires-Dist: asgiref
Provides-Extra: brotli
Requires-Dist: brotli; extra == 'brotli'
